deltacd-0.9.2.dist-info/licenses/LICENSE
utils/__init__.py
utils/daily2mon.py
utils/deltacd2dsm2.py
utils/utils.py
deltacd-0.9.2.dist-info/METADATA
deltacd-0.9.2.dist-info/WHEEL
deltacd-0.9.2.dist-info/entry_points.txt
deltacd-0.9.2.dist-info/top_level.txt
deltacd-0.9.2.dist-info/RECORD
