Metadata-Version: 2.4
Name: deltacd
Version: 0.9.2
Summary: DeltaCD, Delta Channel Depletion Model
Author-email: California Department of Water Resources <kijin.nam@water.ca.gov>
License-Expression: MIT
Project-URL: Homepage, https://github.com/cadwrdeltamodeling/deltacd
Project-URL: Source, https://github.com/cadwrdeltamodeling/deltacd
Project-URL: Bug Tracker, https://github.com/cadwrdeltamodeling/deltacd/issues
Project-URL: Documentation, https://github.com/cadwrdeltamodeling/deltacd#readme
Keywords: deltacd,hydrology
Classifier: Development Status :: 4 - Beta
Classifier: Intended Audience :: Science/Research
Classifier: Topic :: Scientific/Engineering
Classifier: Programming Language :: Python :: 3.9
Classifier: Programming Language :: Python :: 3.10
Classifier: Programming Language :: Python :: 3.11
Classifier: Programming Language :: Python :: 3.12
Classifier: Natural Language :: English
Classifier: Operating System :: OS Independent
Classifier: Environment :: Console
Requires-Python: <3.13,>=3.9
License-File: LICENSE
Requires-Dist: pandas
Requires-Dist: netcdf4
Requires-Dist: xarray
Requires-Dist: pyyaml
Requires-Dist: numba
Dynamic: license-file
